README.md
setup.py
MSOIPPU.egg-info/PKG-INFO
MSOIPPU.egg-info/SOURCES.txt
MSOIPPU.egg-info/dependency_links.txt
MSOIPPU.egg-info/top_level.txt
flood_tool/__init__.py
flood_tool/analysis.py
flood_tool/geo.py
flood_tool/live.py
flood_tool/mapping.py
flood_tool/tool.py